Workbook

Sheet Constituents2021
A1: =_xll.Thomson.Reuters.AFOSpreadsheetFormulas.DSGRID("LDJSTOXX0121","ISIN","Latest Value","","","RowHeader=true;ColHeader=true;DispSeriesDescription=true;DispDatatypeDescription=true;AutoRefresh=false","") -> #NAME? | B1: ISIN CODE
A2: 960338 | B2: GB00B1YW4409
A3: 997863 | B3: DK0010244508
A4: 685120 | B4: IT0001233417
A5: 31938W | B5: SE0011337708
A6: 749352 | B6: NL0000852564
A7: 922924 | B7: CH0012221716
A8: 8721AT | B8: NL0011540547
A9: 741112 | B9: ES0125220311
A10: 929363 | B10: FR0000120404
A11: 755087 | B11: BE0003764785
A12: 539621 | B12: ES0167050915
A13: 257663 | B13: SE0014781795
A14: 992838 | B14: CH0012138605
A15: 9441K0 | B15: NO0010844038
A16: 870874 | B16: DE000A1EWWW0
A17: 9746D6 | B17: LU1250154413
A18: 29549F | B18: GB00B02J6398
A19: 36066K | B19: FR0010340141
A20: 9307KF | B20: NL0012969182
A21: 41293M | B21: BE0003851681
A22: 922956 | B22: BMG0112X1056
A23: 89240U | B23: ES0105046009
A24: 749488 | B24: SE0005999836
A25: 929303 | B25: BE0974264930
A26: 916642 | B26: NL0011794037
A27: 923295 | B27: FR0000120073
A28: 289361 | B28: NL0000235190
A29: 51429U | B29: NO0010345853
A30: 912643 | B30: NL0013267909
A31: 94405Z | B31: CH0432492467
A32: 25522V | B32: SE0000695876
A33: 9839J3 | B33: LU2237380790
A34: 866033 | B34: DE0008404005
A35: 276819 | B35: CH0008837566
A36: 682858 | B36: FR0010220475
A37: 50367Q | B37: DE000A0LD2U1
A38: 692445 | B38: FR0000071946
A39: 69265H | B39: ES0109067019
A40: 307640 | B40: DK0060946788
A41: 259288 | B41: IT0004056880
A42: 28976M | B42: AT0000A18XM4
A43: 8712AZ | B43: FR0004125920
A44: 255055 | B44: AT0000730007
A45: 903076 | B45: GB00B1XZS820
A46: 289504 | B46: BE0974293251
A47: 926288 | B47: GB0000456144
A48: 899069 | B48: LU1598757687
A49: 8917JF | B49: NL0010832176
A50: 35720C | B50: FR0010313833
A51: 8739DD | B51: LU1673108939
A52: 412726 | B52: GB00B132NW22
A53: 906045 | B53: GB0000536739
A54: 888051 | B54: NL0000334118
A55: 152001 | B55: NL0010273215
A56: 7493HR | B56: NL0011872643
A57: 143328 | B57: SE0007100581
A58: 923375 | B58: IT0000062072
A59: 900825 | B59: GB0006731235
A60: 28065X | B60: GB00BVGBWW93
A61: 319608 | B61: GB0009895292
A62: 685756 | B62: IT0003506190
A63: 929448 | B63: SE0017486889
A64: 740622 | B64: FR0000051732
A65: 9375DV | B65: GB00BVYVFW23
A66: 92981W | B66: GB00BDD85M81
A67: 882839 | B67: GB00BBG9VN75
A68: 901503 | B68: GB00BPQY8M80
A69: 936732 | B69: FR0000120628
A70: 897639 | B70: SE0006993770
A71: 8911X3 | B71: LU1072616219
A72: 901419 | B72: GB0002634946
A73: 69048X | B73: FO0000000179
A74: 929734 | B74: CH0012410517
A75: 682797 | B75: IT0005218380
A76: 906225 | B76: IE00BD1RP616
A77: 756572 | B77: ES0113679I37
A78: 933503 | B78: CH0531751755
A79: 901443 | B79: GB0031348658
A80: 906309 | B80: GB0000811801
A81: 682796 | B81: CH0009002962
A82: 866034 | B82: DE000BASF111
A83: 9175MU | B83: AT0000BAWAG2
A84: 866035 | B84: DE000BAY0017
A85: 779090 | B85: ES0113211835
A86: 258990 | B86: ES0113860A34
A87: 702853 | B87: ES0113900J37
A88: 866096 | B88: NL0012866412
A89: 26473F | B89: GB00BYQ0JC66
A90: 290299 | B90: DE0005158703
A91: 870528 | B91: DE0005200000
A92: 504049 | B92: SE0015949748
A93: 866091 | B93: CH1101098163
A94: 904076 | B94: GB0000904986
A95: 974117 | B95: GB00BLJNXL82
A96: 899188 | B96: GB00BH0P3Z91
A97: 257778 | B97: SE0000862997
A98: 29169X | B98: FR0013280286
A99: 866038 | B99: DE0005190003
A100: 309449 | B100: FR0000131104
...

Sheet Constituents_Identifiers
A1: =_xll.Thomson.Reuters.AFOSpreadsheetFormulas.DSGRID("LDJSTOXX0121","ISIN;NAME","Latest Value","","","RowHeader=true;ColHeader=true;DispSeriesDescription=true;DispDatatypeDescription=true;AutoRefresh=false","") -> #NAME? | B1: ISIN CODE | C1: NAME
A2: 960338 | B2: GB00B1YW4409 | C2: 3I GROUP
A3: 997863 | B3: DK0010244508 | C3: A P MOLLER MAERSK B
A4: 685120 | B4: IT0001233417 | C4: A2A
A5: 31938W | B5: SE0011337708 | C5: AAK
A6: 749352 | B6: NL0000852564 | C6: AALBERTS
A7: 922924 | B7: CH0012221716 | C7: ABB LTD N
A8: 8721AT | B8: NL0011540547 | C8: ABN AMRO BANK
A9: 741112 | B9: ES0125220311 | C9: ACCIONA
A10: 929363 | B10: FR0000120404 | C10: ACCOR
A11: 755087 | B11: BE0003764785 | C11: ACKERMANS & VAN HAAREN
A12: 539621 | B12: ES0167050915 | C12: ACS ACTIV.CONSTR.Y SERV.
A13: 257663 | B13: SE0014781795 | C13: ADDTECH B
A14: 992838 | B14: CH0012138605 | C14: ADECCO GROUP
A15: 9441K0 | B15: NO0010844038 | C15: ADEVINTA
A16: 870874 | B16: DE000A1EWWW0 | C16: ADIDAS (XET)
A17: 9746D6 | B17: LU1250154413 | C17: ADLER GROUP (XET)
A18: 29549F | B18: GB00B02J6398 | C18: ADMIRAL GROUP
A19: 36066K | B19: FR0010340141 | C19: ADP
A20: 9307KF | B20: NL0012969182 | C20: ADYEN
A21: 41293M | B21: BE0003851681 | C21: AEDIFICA
A22: 922956 | B22: BMG0112X1056 | C22: AEGON
A23: 89240U | B23: ES0105046009 | C23: AENA SME
A24: 749488 | B24: SE0005999836 | C24: AFRY
A25: 929303 | B25: BE0974264930 | C25: AGEAS (EX-FORTIS)
A26: 916642 | B26: NL0011794037 | C26: KONINKLIJKE AHOLD DELHAIZE
A27: 923295 | B27: FR0000120073 | C27: L AIR LQE.SC.ANYME. POUR L ETUDE ET L EPXTN.
A28: 289361 | B28: NL0000235190 | C28: AIRBUS
A29: 51429U | B29: NO0010345853 | C29: AKER BP
A30: 912643 | B30: NL0013267909 | C30: AKZO NOBEL
A31: 94405Z | B31: CH0432492467 | C31: ALCON (SWX) ORD SHS
A32: 25522V | B32: SE0000695876 | C32: ALFA LAVAL
A33: 9839J3 | B33: LU2237380790 | C33: ALLEGRO
A34: 866033 | B34: DE0008404005 | C34: ALLIANZ (XET)
A35: 276819 | B35: CH0008837566 | C35: ALLREAL HOLDING
A36: 682858 | B36: FR0010220475 | C36: ALSTOM
A37: 50367Q | B37: DE000A0LD2U1 | C37: ALSTRIA OFFICE REIT(XET)
A38: 692445 | B38: FR0000071946 | C38: ALTEN
A39: 69265H | B39: ES0109067019 | C39: AMADEUS IT GROUP
A40: 307640 | B40: DK0060946788 | C40: AMBU B
A41: 259288 | B41: IT0004056880 | C41: AMPLIFON
A42: 28976M | B42: AT0000A18XM4 | C42: AMS-OSRAM AG
A43: 8712AZ | B43: FR0004125920 | C43: AMUNDI (WI)
A44: 255055 | B44: AT0000730007 | C44: ANDRITZ
A45: 903076 | B45: GB00B1XZS820 | C45: ANGLO AMERICAN
A46: 289504 | B46: BE0974293251 | C46: ANHEUSER-BUSCH INBEV
A47: 926288 | B47: GB0000456144 | C47: ANTOFAGASTA
A48: 899069 | B48: LU1598757687 | C48: ARCELORMITTAL
A49: 8917JF | B49: NL0010832176 | C49: ARGENX
A50: 35720C | B50: FR0010313833 | C50: ARKEMA
A51: 8739DD | B51: LU1673108939 | C51: AROUNDTOWN (XET)
A52: 412726 | B52: GB00B132NW22 | C52: ASHMORE GROUP
A53: 906045 | B53: GB0000536739 | C53: ASHTEAD GROUP
A54: 888051 | B54: NL0000334118 | C54: ASM INTERNATIONAL
A55: 152001 | B55: NL0010273215 | C55: ASML HOLDING
A56: 7493HR | B56: NL0011872643 | C56: ASR NEDERLAND
A57: 143328 | B57: SE0007100581 | C57: ASSA ABLOY B
A58: 923375 | B58: IT0000062072 | C58: ASSICURAZIONI GENERALI
A59: 900825 | B59: GB0006731235 | C59: ASSOCIATED BRIT.FOODS
A60: 28065X | B60: GB00BVGBWW93 | C60: ASSURA
A61: 319608 | B61: GB0009895292 | C61: ASTRAZENECA
A62: 685756 | B62: IT0003506190 | C62: ATLANTIA DEAD - DELIST.09/12/22
A63: 929448 | B63: SE0017486889 | C63: ATLAS COPCO A
A64: 740622 | B64: FR0000051732 | C64: ATOS
A65: 9375DV | B65: GB00BVYVFW23 | C65: AUTO TRADER GROUP
A66: 92981W | B66: GB00BDD85M81 | C66: AVAST DEAD - DELIST.13/09/22
A67: 882839 | B67: GB00BBG9VN75 | C67: AVEVA GROUP DEAD - DELIST.19/01/23
A68: 901503 | B68: GB00BPQY8M80 | C68: AVIVA
A69: 936732 | B69: FR0000120628 | C69: AXA
A70: 897639 | B70: SE0006993770 | C70: AXFOOD
A71: 8911X3 | B71: LU1072616219 | C71: B&M EUROPEAN VAL.RET.
A72: 901419 | B72: GB0002634946 | C72: BAE SYSTEMS
A73: 69048X | B73: FO0000000179 | C73: BAKKAFROST
A74: 929734 | B74: CH0012410517 | C74: BALOISE HOLDING
A75: 682797 | B75: IT0005218380 | C75: BANCO BPM
A76: 906225 | B76: IE00BD1RP616 | C76: BANK OF IRELAND GROUP
A77: 756572 | B77: ES0113679I37 | C77: BANKINTER 'R'
A78: 933503 | B78: CH0531751755 | C78: BC VAUD N
A79: 901443 | B79: GB0031348658 | C79: BARCLAYS
A80: 906309 | B80: GB0000811801 | C80: BARRATT DEVELOPMENTS
A81: 682796 | B81: CH0009002962 | C81: BARRY CALLEBAUT
A82: 866034 | B82: DE000BASF111 | C82: BASF (XET)
A83: 9175MU | B83: AT0000BAWAG2 | C83: BAWAG GROUP
A84: 866035 | B84: DE000BAY0017 | C84: BAYER (XET)
A85: 779090 | B85: ES0113211835 | C85: BBV.ARGENTARIA
A86: 258990 | B86: ES0113860A34 | C86: BANCO DE SABADELL
A87: 702853 | B87: ES0113900J37 | C87: BANCO SANTANDER
A88: 866096 | B88: NL0012866412 | C88: BE SEMICONDUCTOR INDUSTRIES
A89: 26473F | B89: GB00BYQ0JC66 | C89: BEAZLEY
A90: 290299 | B90: DE0005158703 | C90: BECHTLE (XET)
A91: 870528 | B91: DE0005200000 | C91: BEIERSDORF (XET)
A92: 504049 | B92: SE0015949748 | C92: BEIJER REF B
A93: 866091 | B93: CH1101098163 | C93: BELIMO N
A94: 904076 | B94: GB0000904986 | C94: BELLWAY
A95: 974117 | B95: GB00BLJNXL82 | C95: BERKELEY GROUP HOLDINGS (THE)
A96: 899188 | B96: GB00BH0P3Z91 | C96: BHP GROUP DEAD - DELIST.31/01/22
A97: 257778 | B97: SE0000862997 | C97: BILLERUD AKTIEBOLAG
A98: 29169X | B98: FR0013280286 | C98: BIOMERIEUX
A99: 866038 | B99: DE0005190003 | C99: BMW (XET)
A100: 309449 | B100: FR0000131104 | C100: BNP PARIBAS
...

Sheet FinancialData
A1: Name | B1: 2021 | C1: 2022 | D1: 2023
A2: 3I GROUP PLC - COMMON SHAREHOLDERS' EQUITY | B2: 9164000 | C2: 12754000 | D2: 16844000
A3: 3I GROUP PLC - TOTAL ASSETS | B3: 10333000 | C3: 13947000 | D3: 17819000
A4: #ERROR | B4: $$ER: 4540,NO DATA VALUES FOUND
A5: 3I GROUP PLC - TOTAL DEBT | B5: 992000 | C5: 989000 | D5: 785000
A6: 3I GROUP PLC - TOTAL LIABILITIES | B6: 1169000 | C6: 1193000 | D6: 975000
A7: #ERROR | B7: $$ER: 4540,NO DATA VALUES FOUND
A8: #ERROR | B8: $$ER: 4540,NO DATA VALUES FOUND
A9: 3I GROUP PLC - NET INCOME - BASIC | B9: 1855000 | C9: 4013000 | D9: 4573000
A10: 3I GROUP PLC - NET INCOME AVAILABLE TO COMMON | B10: 1855000 | C10: 4013000 | D10: 4573000
A11: 3I GROUP PLC - NET INCOME (U.S.$) | B11: 2555096 | C11: 5273323 | D11: 5638738
A12: 3I GROUP PLC - NET SALES OR REVENUES | B12: 739000 | C12: 2411000 | D12: 2758000
A13: 3I GROUP PLC - COST OF GOODS SOLD (EXCL DEP) | B13: 6000 | C13: 46000 | D13: 38000
A14: 3I GROUP PLC - EARNINGS BEF INTEREST & TAXES | B14: 1903000 | C14: 4071000 | D14: 4629000
A15: 3I GROUP PLC - EBIT & DEPRECIATION | B15: 1910000 | C15: 4078000 | D15: 4635000
A16: 3I GROUP PLC - INTEREST EXPENSE - TOTAL | B16: 48000 | C16: 53000 | D16: 54000
A17: 3I GROUP PLC - CASH - GENERIC | B17: 226000 | C17: 222000 | D17: 210000
A18: #ERROR | B18: $$ER: 4540,NO DATA VALUES FOUND
A19: #ERROR | B19: $$ER: 4540,NO DATA VALUES FOUND
A20: 3I GROUP PLC - TOTAL INVENTORIES | B20: 0 | C20: 0 | D20: 0
A21: #ERROR | B21: $$ER: 4540,NO DATA VALUES FOUND
A22: 3I GROUP PLC - CASH FLOW PER SHARE | B22: -0.688 | C22: 0.484 | D22: 0.511
A23: #ERROR | B23: $$ER: 4540,NO DATA VALUES FOUND
A24: #ERROR | B24: $$ER: 4540,NO DATA VALUES FOUND
A25: #ERROR | B25: $$ER: 4540,NO DATA VALUES FOUND
A26: #ERROR | B26: $$ER: 4540,NO DATA VALUES FOUND
A27: 3I GROUP PLC - LONG TERM DEBT | B27: 988000 | C27: 784000 | D27: 780000
A28: 3I GROUP PLC - SHORT TERM DEBT & CURRENT PORT | B28: 4000 | C28: 205000 | D28: 5000
A29: 3I GROUP PLC - SALARIES & BENEFITS EXPENSES | B29: 76000 | C29: 89000 | D29: 97000
A30: 3I GROUP PLC - TOTAL INVESTMENTS | B30: 5026000 | C30: 6649000 | D30: 9591000
A31: 3I GROUP PLC - TOTAL CAPITAL | B31: 10152000 | C31: 13538000 | D31: 17624000
A32: 3I GROUP PLC - TOTAL SHAREHOLDERS EQUITY | B32: 9164000 | C32: 12754000 | D32: 16844000
A33: 3I GROUP PLC - GROSS PROFIT MARGIN | B33: 98.24 | C33: 97.8 | D33: 98.4
A34: 3I GROUP PLC - GROSS INCOME | B34: 726000 | C34: 2358000 | D34: 2714000
A35: 3I GROUP PLC - RETAINED EARNINGS | B35: 7726000 | C35: 11352000 | D35: 15445000
A36: 3I GROUP PLC - RECEIVABLES(NET) | B36: 19000 | C36: 61000 | D36: 44000
A37: 3I GROUP PLC - CASH - GENERIC | B37: 226000 | C37: 222000 | D37: 210000
A38: 3I GROUP PLC - NUMBER OF SHARES | B38: 973136 | C38: 973211 | D38: 973289
A39: #ERROR | B39: $$ER: E100,INVALID CODE OR EXPRESSION ENTERED
A40: #ERROR | B40: $$ER: E100,INVALID CODE OR EXPRESSION ENTERED
A41: AP MOELLER - MAERSK - COMMON SHAREHOLDERS' EQUITY | B41: 291130389 | C41: 444536518 | D41: 364968868
A42: AP MOELLER - MAERSK - TOTAL ASSETS | B42: 470401768 | C42: 648010048 | D42: 552262812
A43: AP MOELLER - MAERSK - CURRENT ASSETS - TOTAL | B43: 168772946 | C43: 278312052 | D43: 209551438
A44: AP MOELLER - MAERSK - TOTAL DEBT | B44: 100307462 | C44: 108669731 | D44: 100067533
A45: AP MOELLER - MAERSK - TOTAL LIABILITIES | B45: 172207013 | C45: 196241848 | D45: 180133718
A46: AP MOELLER - MAERSK - CURRENT LIABILITIES-TOTAL | B46: 79101280 | C46: 92539122 | D46: 83700338
A47: #ERROR | B47: $$ER: 4540,NO DATA VALUES FOUND
A48: AP MOELLER - MAERSK - NET INCOME - BASIC | B48: 113106009 | C48: 206273359 | D48: 26324140
A49: AP MOELLER - MAERSK - NET INCOME AVAILABLE TO COMMON | B49: 113106009 | C49: 206273359 | D49: 26324140
A50: AP MOELLER - MAERSK - NET INCOME (U.S.$) | B50: 17291647 | C50: 29693050 | D50: 3897026
A51: AP MOELLER - MAERSK - NET SALES OR REVENUES | B51: 389504012 | C51: 575973035 | D51: 351711719
A52: AP MOELLER - MAERSK - COST OF GOODS SOLD (EXCL DEP) | B52: 237950029 | C52: 317075172 | D52: 285439906
A53: AP MOELLER - MAERSK - EARNINGS BEF INTEREST & TAXES | B53: 122933914 | C53: 218982646 | D53: 35284816
A54: AP MOELLER - MAERSK - EBIT & DEPRECIATION | B54: 151907006 | C54: 261087900 | D54: 78249228
A55: #ERROR | B55: $$ER: 4540,NO DATA VALUES FOUND
A56: AP MOELLER - MAERSK - CASH - GENERIC | B56: 77413682 | C56: 76408513 | D56: 45264786
A57: AP MOELLER - MAERSK - ACCOUNTS PAYABLE | B57: 40822880 | C57: 47266435 | D57: 43238307
A58: AP MOELLER - MAERSK - ACCOUNTS RECEIVABLES DAYS | B58: 50 | C58: 82 | D58: 163
A59: AP MOELLER - MAERSK - TOTAL INVENTORIES | B59: 9530354 | C59: 11142763 | D59: 11199674
A60: AP MOELLER - MAERSK - PREPAID EXPENSES | B60: 3545265 | C60: 8648841 | D60: 8572006
A61: AP MOELLER - MAERSK - CASH FLOW PER SHARE | B61: 7658.962 | C61: 13879.032 | D61: 3996.319
A62: #ERROR | B62: $$ER: 4540,NO DATA VALUES FOUND
A63: #ERROR | B63: $$ER: 4540,NO DATA VALUES FOUND
A64: #ERROR | B64: $$ER: 4540,NO DATA VALUES FOUND
A65: #ERROR | B65: $$ER: 4540,NO DATA VALUES FOUND
A66: AP MOELLER - MAERSK - LONG TERM DEBT | B66: 81554185 | C66: 85835402 | D66: 80836247
A67: AP MOELLER - MAERSK - SHORT TERM DEBT & CURRENT PORT | B67: 18753276 | C67: 22834329 | D67: 19231286
A68: AP MOELLER - MAERSK - SALARIES & BENEFITS EXPENSES | B68: 38656005 | C68: 50067104 | D68: 50699108
A69: #ERROR | B69: $$ER: 4540,NO DATA VALUES FOUND
A70: AP MOELLER - MAERSK - TOTAL CAPITAL | B70: 379748940 | C70: 537603602 | D70: 452965341
A71: AP MOELLER - MAERSK - TOTAL SHAREHOLDERS EQUITY | B71: 291130389 | C71: 444536518 | D71: 364968868
A72: AP MOELLER - MAERSK - GROSS PROFIT MARGIN | B72: 31.47 | C72: 37.64 | D72: 6.63
A73: AP MOELLER - MAERSK - GROSS INCOME | B73: 122580891 | C73: 216792608 | D73: 23307402
A74: AP MOELLER - MAERSK - RETAINED EARNINGS | B74: 273332110 | C74: 428246132 | D74: 350053982
A75: AP MOELLER - MAERSK - RECEIVABLES(NET) | B75: 75673755 | C75: 181632602 | D75: 132423648
A76: AP MOELLER - MAERSK - CASH - GENERIC | B76: 77413682 | C76: 76408513 | D76: 45264786
A77: AP MOELLER - MAERSK - NUMBER OF SHARES | B77: 9433 | C77: 8908 | D77: 8373
A78: #ERROR | B78: $$ER: E100,INVALID CODE OR EXPRESSION ENTERED
A79: #ERROR | B79: $$ER: E100,INVALID CODE OR EXPRESSION ENTERED
A80: A2A SPA - COMMON SHAREHOLDERS' EQUITY | B80: 3760000 | C80: 3899000 | D80: 4240000
A81: A2A SPA - TOTAL ASSETS | B81: 17584000 | C81: 21004000 | D81: 18334000
A82: A2A SPA - CURRENT ASSETS - TOTAL | B82: 8587000 | C82: 11138000 | D82: 7826000
A83: A2A SPA - TOTAL DEBT | B83: 5068000 | C83: 6889000 | D83: 6351000
A84: A2A SPA - TOTAL LIABILITIES | B84: 13281000 | C84: 16537000 | D84: 13532000
A85: A2A SPA - CURRENT LIABILITIES-TOTAL | B85: 8148000 | C85: 9686000 | D85: 7020000
A86: #ERROR | B86: $$ER: 4540,NO DATA VALUES FOUND
A87: A2A SPA - NET INCOME - BASIC | B87: 504000 | C87: 401000 | D87: 659000
A88: A2A SPA - NET INCOME AVAILABLE TO COMMON | B88: 504000 | C88: 401000 | D88: 659000
A89: A2A SPA - NET INCOME (U.S.$) | B89: 572725 | C89: 429335 | D89: 727371
A90: A2A SPA - NET SALES OR REVENUES | B90: 11549000 | C90: 23166000 | D90: 14758000
A91: A2A SPA - COST OF GOODS SOLD (EXCL DEP) | B91: 9096000 | C91: 20522000 | D91: 11589000
A92: A2A SPA - EARNINGS BEF INTEREST & TAXES | B92: 658000 | C92: 848000 | D92: 1046000
A93: A2A SPA - EBIT & DEPRECIATION | B93: 1324000 | C93: 1572000 | D93: 1847000
A94: #ERROR | B94: $$ER: 4540,NO DATA VALUES FOUND
A95: A2A SPA - CASH - GENERIC | B95: 4710000 | C95: 5459000 | D95: 3188000
A96: A2A SPA - ACCOUNTS PAYABLE | B96: 2886000 | C96: 5481000 | D96: 4099000
A97: A2A SPA - ACCOUNTS RECEIVABLES DAYS | B97: 91 | C97: 67 | D97: 109
A98: A2A SPA - TOTAL INVENTORIES | B98: 204000 | C98: 536000 | D98: 319000
A99: A2A SPA - PREPAID EXPENSES | B99: 42000 | C99: 10000 | D99: 12000
A100: A2A SPA - CASH FLOW PER SHARE | B100: 0.386 | C100: 0.404 | D100: 0.501
...

Sheet IndustryClassifier2021
A1: ISIN | B1: INDUSTRY GROUP | C1: SIC CODE 1 | D1: SIC CODE 2 | E1: SIC CODE 3 | F1: INDM
A2: GB00B1YW4409 | B2: 109 | C2: 6799 | F2: =INDEX(Industries!$D$2:$D$473,MATCH(B2,Industries!$B$2:$B$473,0)) -> Investment Trusts
A3: DK0010244508 | B3: 99 | C3: 4412 | D3: 4491 | E3: 1389 | F3: =INDEX(Industries!$D$2:$D$473,MATCH(B3,Industries!$B$2:$B$473,0)) -> Marine Transportation
A4: IT0001233417 | B4: 169 | C4: 4911 | D4: 4924 | E4: 4941 | F4: =INDEX(Industries!$D$2:$D$473,MATCH(B4,Industries!$B$2:$B$473,0)) -> Conv. Electricity
A5: SE0011337708 | B5: 71 | C5: 2079 | D5: 2869 | E5: 2035 | F5: =INDEX(Industries!$D$2:$D$473,MATCH(B5,Industries!$B$2:$B$473,0)) -> Food Products
A6: NL0000852564 | B6: 213 | C6: 3498 | D6: 3491 | E6: 3492 | F6: =INDEX(Industries!$D$2:$D$473,MATCH(B6,Industries!$B$2:$B$473,0)) -> Elec. Eq: Control
A7: CH0012221716 | B7: 258 | C7: 3613 | D7: 3612 | E7: 3823 | F7: =INDEX(Industries!$D$2:$D$473,MATCH(B7,Industries!$B$2:$B$473,0)) -> Electrical Components
A8: NL0011540547 | B8: 102 | C8: 6029 | D8: 6331 | E8: 6311 | F8: =INDEX(Industries!$D$2:$D$473,MATCH(B8,Industries!$B$2:$B$473,0)) -> Banks
A9: ES0125220311 | B9: 39 | C9: 1629 | D9: 8711 | E9: 1611 | F9: =INDEX(Industries!$D$2:$D$473,MATCH(B9,Industries!$B$2:$B$473,0)) -> Construction
A10: FR0000120404 | B10: 80 | C10: 7011 | D10: 6719 | F10: =INDEX(Industries!$D$2:$D$473,MATCH(B10,Industries!$B$2:$B$473,0)) -> Hotels & Motels
A11: BE0003764785 | B11: 216 | C11: 1629 | D11: 1541 | E11: 1623 | F11: =INDEX(Industries!$D$2:$D$473,MATCH(B11,Industries!$B$2:$B$473,0)) -> Eng. & Contract Svs
A12: ES0167050915 | B12: 39 | C12: 1611 | D12: 1623 | E12: 1541 | F12: =INDEX(Industries!$D$2:$D$473,MATCH(B12,Industries!$B$2:$B$473,0)) -> Construction
A13: SE0014781795 | B13: 258 | C13: 5084 | D13: 5063 | E13: 5065 | F13: =INDEX(Industries!$D$2:$D$473,MATCH(B13,Industries!$B$2:$B$473,0)) -> Electrical Components
A14: CH0012138605 | B14: 134 | C14: 7363 | D14: 8742 | E14: 7361 | F14: =INDEX(Industries!$D$2:$D$473,MATCH(B14,Industries!$B$2:$B$473,0)) -> Training, Emp. Agency
A15: NO0010844038 | B15: 156 | C15: 7375 | F15: =INDEX(Industries!$D$2:$D$473,MATCH(B15,Industries!$B$2:$B$473,0)) -> Consumer Svs: Misc.
A16: DE000A1EWWW0 | B16: 153 | C16: 3149 | D16: 2252 | E16: 2329 | F16: =INDEX(Industries!$D$2:$D$473,MATCH(B16,Industries!$B$2:$B$473,0)) -> Footwear
A17: LU1250154413 | B17: 112 | C17: 6513 | D17: 6531 | F17: =INDEX(Industries!$D$2:$D$473,MATCH(B17,Industries!$B$2:$B$473,0)) -> Real Estate Hold, Dev
A18: GB00B02J6398 | B18: 107 | C18: 6331 | D18: 6411 | E18: 6719 | F18: =INDEX(Industries!$D$2:$D$473,MATCH(B18,Industries!$B$2:$B$473,0)) -> Prop. & Casualty Ins.
A19: FR0010340141 | B19: 64 | C19: 4581 | D19: 7389 | F19: =INDEX(Industries!$D$2:$D$473,MATCH(B19,Industries!$B$2:$B$473,0)) -> Transport Services
A20: NL0012969182 | B20: 261 | C20: 7372 | F20: =INDEX(Industries!$D$2:$D$473,MATCH(B20,Industries!$B$2:$B$473,0)) -> Transaction Process
A21: BE0003851681 | B21: 222 | C21: 6513 | F21: =INDEX(Industries!$D$2:$D$473,MATCH(B21,Industries!$B$2:$B$473,0)) -> Health Care REITs
A22: BMG0112X1056 | B22: 106 | C22: 6311 | D22: 6324 | E22: 6331 | F22: =INDEX(Industries!$D$2:$D$473,MATCH(B22,Industries!$B$2:$B$473,0)) -> Life Insurance
A23: ES0105046009 | B23: 64 | C23: 4581 | F23: =INDEX(Industries!$D$2:$D$473,MATCH(B23,Industries!$B$2:$B$473,0)) -> Transport Services
A24: SE0005999836 | B24: 216 | C24: 8711 | D24: 1542 | E24: 3822 | F24: =INDEX(Industries!$D$2:$D$473,MATCH(B24,Industries!$B$2:$B$473,0)) -> Eng. & Contract Svs
A25: BE0974264930 | B25: 106 | C25: 6411 | D25: 6311 | E25: 6331 | F25: =INDEX(Industries!$D$2:$D$473,MATCH(B25,Industries!$B$2:$B$473,0)) -> Life Insurance
A26: NL0011794037 | B26: 88 | C26: 5411 | F26: =INDEX(Industries!$D$2:$D$473,MATCH(B26,Industries!$B$2:$B$473,0)) -> Food Retail & Wsale
A27: FR0000120073 | B27: 33 | C27: 2813 | D27: 5169 | E27: 8711 | F27: =INDEX(Industries!$D$2:$D$473,MATCH(B27,Industries!$B$2:$B$473,0)) -> Specialty Chemicals
A28: NL0000235190 | B28: 98 | C28: 3721 | D28: 3728 | E28: 3761 | F28: =INDEX(Industries!$D$2:$D$473,MATCH(B28,Industries!$B$2:$B$473,0)) -> Aerospace
A29: NO0010345853 | B29: 50 | C29: 1311 | D29: 1389 | F29: =INDEX(Industries!$D$2:$D$473,MATCH(B29,Industries!$B$2:$B$473,0)) -> Oil: Crude Producers
A30: NL0013267909 | B30: 33 | C30: 2851 | D30: 2821 | F30: =INDEX(Industries!$D$2:$D$473,MATCH(B30,Industries!$B$2:$B$473,0)) -> Specialty Chemicals
A31: CH0432492467 | B31: 103 | C31: 3589 | D31: 3841 | E31: 3851 | F31: =INDEX(Industries!$D$2:$D$473,MATCH(B31,Industries!$B$2:$B$473,0)) -> Medical Supplies
A32: SE0000695876 | B32: 213 | C32: 3585 | F32: =INDEX(Industries!$D$2:$D$473,MATCH(B32,Industries!$B$2:$B$473,0)) -> Elec. Eq: Control
A33: LU2237380790 | B33: 156 | C33: 5999 | F33: =INDEX(Industries!$D$2:$D$473,MATCH(B33,Industries!$B$2:$B$473,0)) -> Consumer Svs: Misc.
A34: DE0008404005 | B34: 141 | C34: 6311 | D34: 6324 | E34: 6331 | F34: =INDEX(Industries!$D$2:$D$473,MATCH(B34,Industries!$B$2:$B$473,0)) -> Full Line Insurance
A35: CH0008837566 | B35: 112 | C35: 1542 | D35: 1531 | E35: 6531 | F35: =INDEX(Industries!$D$2:$D$473,MATCH(B35,Industries!$B$2:$B$473,0)) -> Real Estate Hold, Dev
A36: FR0010220475 | B36: 258 | C36: 3743 | D36: 3711 | E36: 1629 | F36: =INDEX(Industries!$D$2:$D$473,MATCH(B36,Industries!$B$2:$B$473,0)) -> Electrical Components
A37: DE000A0LD2U1 | B37: 239 | C37: 6512 | D37: 6531 | F37: =INDEX(Industries!$D$2:$D$473,MATCH(B37,Industries!$B$2:$B$473,0)) -> Office REITs
A38: FR0000071946 | B38: 150 | C38: 7373 | F38: =INDEX(Industries!$D$2:$D$473,MATCH(B38,Industries!$B$2:$B$473,0)) -> Computer Services
A39: ES0109067019 | B39: 150 | C39: 7373 | D39: 7371 | E39: 7376 | F39: =INDEX(Industries!$D$2:$D$473,MATCH(B39,Industries!$B$2:$B$473,0)) -> Computer Services
A40: DK0060946788 | B40: 132 | C40: 3841 | D40: 3842 | F40: =INDEX(Industries!$D$2:$D$473,MATCH(B40,Industries!$B$2:$B$473,0)) -> Medical Equipment
A41: IT0004056880 | B41: 103 | C41: 5499 | F41: =INDEX(Industries!$D$2:$D$473,MATCH(B41,Industries!$B$2:$B$473,0)) -> Medical Supplies
A42: AT0000A18XM4 | B42: 130 | C42: 3674 | D42: 3822 | E42: 3823 | F42: =INDEX(Industries!$D$2:$D$473,MATCH(B42,Industries!$B$2:$B$473,0)) -> Semiconductors
A43: FR0004125920 | B43: 104 | C43: 6282 | F43: =INDEX(Industries!$D$2:$D$473,MATCH(B43,Industries!$B$2:$B$473,0)) -> Asset Mngr, Custodian
A44: AT0000730007 | B44: 43 | C44: 3553 | D44: 3547 | E44: 3589 | F44: =INDEX(Industries!$D$2:$D$473,MATCH(B44,Industries!$B$2:$B$473,0)) -> Machinery: Industrial
A45: GB00B1XZS820 | B45: 122 | C45: 1011 | D45: 1021 | E45: 1499 | F45: =INDEX(Industries!$D$2:$D$473,MATCH(B45,Industries!$B$2:$B$473,0)) -> General Mining
A46: BE0974293251 | B46: 67 | C46: 2082 | F46: =INDEX(Industries!$D$2:$D$473,MATCH(B46,Industries!$B$2:$B$473,0)) -> Brewers
A47: GB0000456144 | B47: 209 | C47: 1021 | D47: 1041 | E47: 4213 | F47: =INDEX(Industries!$D$2:$D$473,MATCH(B47,Industries!$B$2:$B$473,0)) -> Copper
A48: LU1598757687 | B48: 56 | C48: 3312 | D48: 3317 | E48: 3316 | F48: =INDEX(Industries!$D$2:$D$473,MATCH(B48,Industries!$B$2:$B$473,0)) -> Iron & Steel
A49: NL0010832176 | B49: 157 | C49: 8731 | F49: =INDEX(Industries!$D$2:$D$473,MATCH(B49,Industries!$B$2:$B$473,0)) -> Biotechnology
A50: FR0010313833 | B50: 92 | C50: 2819 | D50: 2821 | E50: 2891 | F50: =INDEX(Industries!$D$2:$D$473,MATCH(B50,Industries!$B$2:$B$473,0)) -> Chemicals: Divers.
A51: LU1673108939 | B51: 112 | C51: 6512 | D51: 6513 | F51: =INDEX(Industries!$D$2:$D$473,MATCH(B51,Industries!$B$2:$B$473,0)) -> Real Estate Hold, Dev
A52: GB00B132NW22 | B52: 104 | C52: 6282 | F52: =INDEX(Industries!$D$2:$D$473,MATCH(B52,Industries!$B$2:$B$473,0)) -> Asset Mngr, Custodian
A53: GB0000536739 | B53: 208 | C53: 7359 | D53: 6719 | F53: =INDEX(Industries!$D$2:$D$473,MATCH(B53,Industries!$B$2:$B$473,0)) -> Comm. Vehicles, Lease
A54: NL0000334118 | B54: 245 | C54: 3559 | F54: =INDEX(Industries!$D$2:$D$473,MATCH(B54,Industries!$B$2:$B$473,0)) -> Prod. Tech. Equipment
A55: NL0010273215 | B55: 245 | C55: 3559 | D55: 6719 | F55: =INDEX(Industries!$D$2:$D$473,MATCH(B55,Industries!$B$2:$B$473,0)) -> Prod. Tech. Equipment
A56: NL0011872643 | B56: 141 | C56: 6311 | D56: 6331 | E56: 6324 | F56: =INDEX(Industries!$D$2:$D$473,MATCH(B56,Industries!$B$2:$B$473,0)) -> Full Line Insurance
A57: SE0007100581 | B57: 30 | C57: 7699 | D57: 3442 | E57: 3429 | F57: =INDEX(Industries!$D$2:$D$473,MATCH(B57,Industries!$B$2:$B$473,0)) -> Bldg Materials: Other
A58: IT0000062072 | B58: 141 | C58: 6311 | D58: 6324 | E58: 6331 | F58: =INDEX(Industries!$D$2:$D$473,MATCH(B58,Industries!$B$2:$B$473,0)) -> Full Line Insurance
A59: GB0006731235 | B59: 71 | C59: 5651 | D59: 2035 | E59: 2015 | F59: =INDEX(Industries!$D$2:$D$473,MATCH(B59,Industries!$B$2:$B$473,0)) -> Food Products
A60: GB00BVGBWW93 | B60: 222 | C60: 6512 | F60: =INDEX(Industries!$D$2:$D$473,MATCH(B60,Industries!$B$2:$B$473,0)) -> Health Care REITs
A61: GB0009895292 | B61: 95 | C61: 2834 | D61: 8731 | E61: 6719 | F61: =INDEX(Industries!$D$2:$D$473,MATCH(B61,Industries!$B$2:$B$473,0)) -> Pharmaceuticals
A62: IT0003506190 | B62: 64 | C62: 4231 | D62: 4581 | E62: 3663 | F62: =INDEX(Industries!$D$2:$D$473,MATCH(B62,Industries!$B$2:$B$473,0)) -> Transport Services
A63: SE0017486889 | B63: 229 | C63: 3563 | D63: 3491 | E63: 3546 | F63: =INDEX(Industries!$D$2:$D$473,MATCH(B63,Industries!$B$2:$B$473,0)) -> Machinery: Const.
A64: FR0000051732 | B64: 150 | C64: 7373 | D64: 7376 | E64: 7371 | F64: =INDEX(Industries!$D$2:$D$473,MATCH(B64,Industries!$B$2:$B$473,0)) -> Computer Services
A65: GB00BVYVFW23 | B65: 151 | C65: 7375 | D65: 7312 | F65: =INDEX(Industries!$D$2:$D$473,MATCH(B65,Industries!$B$2:$B$473,0)) -> Consumer Digital Svs
A66: GB00BDD85M81 | B66: 58 | C66: 7372 | F66: =INDEX(Industries!$D$2:$D$473,MATCH(B66,Industries!$B$2:$B$473,0)) -> Software
A67: GB00BBG9VN75 | B67: 58 | C67: 7371 | D67: 7373 | E67: 8999 | F67: =INDEX(Industries!$D$2:$D$473,MATCH(B67,Industries!$B$2:$B$473,0)) -> Software
A68: GB00BPQY8M80 | B68: 106 | C68: 6311 | D68: 6331 | E68: 6282 | F68: =INDEX(Industries!$D$2:$D$473,MATCH(B68,Industries!$B$2:$B$473,0)) -> Life Insurance
A69: FR0000120628 | B69: 141 | C69: 6311 | D69: 6324 | E69: 6331 | F69: =INDEX(Industries!$D$2:$D$473,MATCH(B69,Industries!$B$2:$B$473,0)) -> Full Line Insurance
A70: SE0006993770 | B70: 88 | C70: 5411 | D70: 5311 | E70: 5141 | F70: =INDEX(Industries!$D$2:$D$473,MATCH(B70,Industries!$B$2:$B$473,0)) -> Food Retail & Wsale
A71: LU1072616219 | B71: 87 | C71: 5311 | F71: =INDEX(Industries!$D$2:$D$473,MATCH(B71,Industries!$B$2:$B$473,0)) -> Diversified Retailers
A72: GB0002634946 | B72: 44 | C72: 3721 | D72: 3728 | E72: 3761 | F72: =INDEX(Industries!$D$2:$D$473,MATCH(B72,Industries!$B$2:$B$473,0)) -> Defense
A73: FO0000000179 | B73: 35 | C73: 273 | D73: 2092 | F73: =INDEX(Industries!$D$2:$D$473,MATCH(B73,Industries!$B$2:$B$473,0)) -> Farming, Fishing
A74: CH0012410517 | B74: 141 | C74: 6311 | D74: 6324 | E74: 6331 | F74: =INDEX(Industries!$D$2:$D$473,MATCH(B74,Industries!$B$2:$B$473,0)) -> Full Line Insurance
A75: IT0005218380 | B75: 102 | C75: 6029 | D75: 6035 | E75: 6159 | F75: =INDEX(Industries!$D$2:$D$473,MATCH(B75,Industries!$B$2:$B$473,0)) -> Banks
A76: IE00BD1RP616 | B76: 102 | C76: 6029 | D76: 6311 | E76: 6211 | F76: =INDEX(Industries!$D$2:$D$473,MATCH(B76,Industries!$B$2:$B$473,0)) -> Banks
A77: ES0113679I37 | B77: 102 | C77: 6029 | D77: 6211 | E77: 6282 | F77: =INDEX(Industries!$D$2:$D$473,MATCH(B77,Industries!$B$2:$B$473,0)) -> Banks
A78: CH0531751755 | B78: 102 | C78: 6029 | D78: 6211 | E78: 6035 | F78: =INDEX(Industries!$D$2:$D$473,MATCH(B78,Industries!$B$2:$B$473,0)) -> Banks
A79: GB0031348658 | B79: 102 | C79: 6029 | D79: 6211 | E79: 6282 | F79: =INDEX(Industries!$D$2:$D$473,MATCH(B79,Industries!$B$2:$B$473,0)) -> Banks
A80: GB0000811801 | B80: 36 | C80: 1531 | D80: 6552 | E80: 6719 | F80: =INDEX(Industries!$D$2:$D$473,MATCH(B80,Industries!$B$2:$B$473,0)) -> Home Construction
A81: CH0009002962 | B81: 71 | C81: 2066 | D81: 5149 | F81: =INDEX(Industries!$D$2:$D$473,MATCH(B81,Industries!$B$2:$B$473,0)) -> Food Products
A82: DE000BASF111 | B82: 92 | C82: 2851 | D82: 2821 | E82: 2869 | F82: =INDEX(Industries!$D$2:$D$473,MATCH(B82,Industries!$B$2:$B$473,0)) -> Chemicals: Divers.
A83: AT0000BAWAG2 | B83: 102 | C83: 6029 | D83: 6159 | E83: 6289 | F83: =INDEX(Industries!$D$2:$D$473,MATCH(B83,Industries!$B$2:$B$473,0)) -> Banks
A84: DE000BAY0017 | B84: 95 | C84: 2834 | D84: 2833 | E84: 8731 | F84: =INDEX(Industries!$D$2:$D$473,MATCH(B84,Industries!$B$2:$B$473,0)) -> Pharmaceuticals
A85: ES0113211835 | B85: 102 | C85: 6029 | D85: 6211 | E85: 6282 | F85: =INDEX(Industries!$D$2:$D$473,MATCH(B85,Industries!$B$2:$B$473,0)) -> Banks
A86: ES0113860A34 | B86: 102 | C86: 6029 | D86: 6211 | E86: 6331 | F86: =INDEX(Industries!$D$2:$D$473,MATCH(B86,Industries!$B$2:$B$473,0)) -> Banks
A87: ES0113900J37 | B87: 102 | C87: 6029 | D87: 6289 | E87: 6311 | F87: =INDEX(Industries!$D$2:$D$473,MATCH(B87,Industries!$B$2:$B$473,0)) -> Banks
A88: NL0012866412 | B88: 130 | C88: 3674 | D88: 3559 | E88: 6719 | F88: =INDEX(Industries!$D$2:$D$473,MATCH(B88,Industries!$B$2:$B$473,0)) -> Semiconductors
A89: GB00BYQ0JC66 | B89: 107 | C89: 6331 | D89: 6311 | E89: 6324 | F89: =INDEX(Industries!$D$2:$D$473,MATCH(B89,Industries!$B$2:$B$473,0)) -> Prop. & Casualty Ins.
A90: DE0005158703 | B90: 150 | C90: 7371 | D90: 7372 | E90: 5999 | F90: =INDEX(Industries!$D$2:$D$473,MATCH(B90,Industries!$B$2:$B$473,0)) -> Computer Services
A91: DE0005200000 | B91: 48 | C91: 2844 | D91: 2841 | F91: =INDEX(Industries!$D$2:$D$473,MATCH(B91,Industries!$B$2:$B$473,0)) -> Personal Products
A92: SE0015949748 | B92: 231 | C92: 3585 | D92: 5078 | E92: 5084 | F92: =INDEX(Industries!$D$2:$D$473,MATCH(B92,Industries!$B$2:$B$473,0)) -> Machinery: Specialty
A93: CH1101098163 | B93: 205 | C93: 3593 | D93: 3822 | E93: 6719 | F93: =INDEX(Industries!$D$2:$D$473,MATCH(B93,Industries!$B$2:$B$473,0)) -> Bldg: Climate Control
A94: GB0000904986 | B94: 36 | C94: 1531 | D94: 6719 | F94: =INDEX(Industries!$D$2:$D$473,MATCH(B94,Industries!$B$2:$B$473,0)) -> Home Construction
A95: GB00BLJNXL82 | B95: 36 | C95: 1531 | D95: 1542 | E95: 6552 | F95: =INDEX(Industries!$D$2:$D$473,MATCH(B95,Industries!$B$2:$B$473,0)) -> Home Construction
A96: GB00BH0P3Z91 | B96: 122 | C96: 1011 | D96: 1021 | E96: 1041 | F96: =INDEX(Industries!$D$2:$D$473,MATCH(B96,Industries!$B$2:$B$473,0)) -> General Mining
A97: SE0000862997 | B97: 82 | C97: 2621 | D97: 2631 | E97: 2653 | F97: =INDEX(Industries!$D$2:$D$473,MATCH(B97,Industries!$B$2:$B$473,0)) -> Paper
A98: FR0013280286 | B98: 132 | C98: 2835 | D98: 3826 | E98: 7372 | F98: =INDEX(Industries!$D$2:$D$473,MATCH(B98,Industries!$B$2:$B$473,0)) -> Medical Equipment
A99: DE0005190003 | B99: 65 | C99: 3711 | D99: 6159 | E99: 6331 | F99: =INDEX(Industries!$D$2:$D$473,MATCH(B99,Industries!$B$2:$B$473,0)) -> Automobiles
A100: FR0000131104 | B100: 102 | C100: 6029 | D100: 6099 | E100: 6153 | F100: =INDEX(Industries!$D$2:$D$473,MATCH(B100,Industries!$B$2:$B$473,0)) -> Banks
...

Sheet Industries
A1: ICB Code | B1: INDG | C1: INDC | D1: INDM | E1: Datastream Sector Level
A2: 10 | B2: 183 | C2: TECNO | D2: Technology | E2: 2
A3: 1010 | B3: 183 | C3: TECNO | D3: Technology | E3: 3
A4: 101010 | B4: 176 | C4: SFTCS | D4: Software & Comp. Svs. | E4: 4
A5: 10101010 | B5: 150 | C5: CMPSV | D5: Computer Services | E5: 5
B6: 150 | C6: CMPSV | D6: Computer Services | E6: 6
A7: 10101015 | B7: 58 | C7: SOFTW | D7: Software | E7: 5
B8: 58 | C8: SOFTW | D8: Software | E8: 6
A9: 10101020 | B9: 151 | C9: CODGT | D9: Consumer Digital Svs | E9: 5
B10: 151 | C10: CODGT | D10: Consumer Digital Svs | E10: 6
A11: 101020 | B11: 175 | C11: TECHD | D11: Tech. Hardware, Equip | E11: 4
A12: 10102010 | B12: 130 | C12: SEMIC | D12: Semiconductors | E12: 5
B13: 130 | C13: SEMIC | D13: Semiconductors | E13: 6
A14: 10102015 | B14: 37 | C14: ELTCC | D14: Electronic Components | E14: 5
B15: 37 | C15: ELTCC | D15: Electronic Components | E15: 6
A16: 10102020 | B16: 245 | C16: PRDTE | D16: Prod. Tech. Equipment | E16: 5
B17: 245 | C17: PRDTE | D17: Prod. Tech. Equipment | E17: 6
A18: 10102030 | B18: 34 | C18: COMPH | D18: Computer Hardware | E18: 5
B19: 34 | C19: COMPH | D19: Computer Hardware | E19: 6
A20: 10102035 | B20: 105 | C20: OFFEQ | D20: Electronic Office Eq. | E20: 5
B21: 105 | C21: OFFEQ | D21: Electronic Office Eq. | E21: 6
A22: 15 | B22: 174 | C22: TELCM | D22: Telecommunications | E22: 2
A23: 1510 | B23: 174 | C23: TELCM | D23: Telecommunications | E23: 3
A24: 151010 | B24: 126 | C24: TELEQ | D24: Telecom. Equipment | E24: 4
A25: 15101010 | B25: 126 | C25: TELEQ | D25: Telecom. Equipment | E25: 5
B26: 126 | C26: TELEQ | D26: Telecom. Equipment | E26: 6
A27: 151020 | B27: 202 | C27: TELSP | D27: Telecom. Svs. Prvds. | E27: 4
A28: 15102010 | B28: 257 | C28: CABTV | D28: Cable TV Services | E28: 5
B29: 257 | C29: CABTV | D29: Cable TV Services | E29: 6
A30: 15102015 | B30: 142 | C30: TELSV | D30: Telecom. Services | E30: 5
B31: 142 | C31: TELSV | D31: Telecom. Services | E31: 6
A32: 20 | B32: 181 | C32: HLTHC | D32: Health Care | E32: 2
A33: 2010 | B33: 181 | C33: HLTHC | D33: Health Care | E33: 3
A34: 201010 | B34: 17 | C34: HLTPR | D34: Health Care Providers | E34: 4
A35: 20101010 | B35: 45 | C35: HCFAC | D35: Health Care Facility | E35: 5
B36: 45 | C36: HCFAC | D36: Health Care Facility | E36: 6
A37: 20101020 | B37: 221 | C37: HLTMS | D37: Health Care Mgmt. Svs | E37: 5
B38: 221 | C38: HLTMS | D38: Health Care Mgmt. Svs | E38: 6
A39: 20101025 | B39: 223 | C39: HLTSV | D39: Health Care Services | E39: 5
B40: 223 | C40: HLTSV | D40: Health Care Services | E40: 6
A41: 20101030 | B41: 224 | C41: HLTMC | D41: Health Care: Misc. | E41: 5
B42: 224 | C42: HLTMC | D42: Health Care: Misc. | E42: 6
A43: 201020 | B43: 172 | C43: MEDES | D43: Medical Eq. Services | E43: 4
A44: 20102010 | B44: 132 | C44: MEDEQ | D44: Medical Equipment | E44: 5
B45: 132 | C45: MEDEQ | D45: Medical Equipment | E45: 6
A46: 20102015 | B46: 103 | C46: MEDSP | D46: Medical Supplies | E46: 5
B47: 103 | C47: MEDSP | D47: Medical Supplies | E47: 6
A48: 20102020 | B48: 233 | C48: MEDSV | D48: Medical Services | E48: 5
B49: 233 | C49: MEDSV | D49: Medical Services | E49: 6
A50: 201030 | B50: 190 | C50: PHARM | D50: Pharm. & Biotech | E50: 4
A51: 20103010 | B51: 157 | C51: BIOTC | D51: Biotechnology | E51: 5
B52: 157 | C52: BIOTC | D52: Biotechnology | E52: 6
A53: 20103015 | B53: 95 | C53: PHRMC | D53: Pharmaceuticals | E53: 5
B54: 95 | C54: PHRMC | D54: Pharmaceuticals | E54: 6
A55: 20103020 | B55: 260 | C55: MJPRD | D55: Cannabis Producers | E55: 5
B56: 260 | C56: MJPRD | D56: Cannabis Producers | E56: 6
A57: 30 | B57: 28 | C57: FINAN | D57: Financials | E57: 2
A58: 3010 | B58: 102 | C58: BANKS | D58: Banks | E58: 3
A59: 301010 | B59: 102 | C59: BANKS | D59: Banks | E59: 4
A60: 30101010 | B60: 102 | C60: BANKS | D60: Banks | E60: 5
B61: 102 | C61: BANKS | D61: Banks | E61: 6
A62: 3020 | B62: 18 | C62: FINSV | D62: Financial Services | E62: 3
A63: 302010 | B63: 168 | C63: FINCS | D63: Finance & Credit Svs | E63: 4
A64: 30201020 | B64: 42 | C64: COLND | D64: Consumer Lending | E64: 5
B65: 42 | C65: COLND | D65: Consumer Lending | E65: 6
A66: 30201025 | B66: 152 | C66: MORTF | D66: Mortgage Finance | E66: 5
B67: 152 | C67: MORTF | D67: Mortgage Finance | E67: 6
A68: 30201030 | B68: 46 | C68: FINDP | D68: Fin. Data Providers | E68: 5
B69: 46 | C69: FINDP | D69: Fin. Data Providers | E69: 6
A70: 302020 | B70: 200 | C70: INVBB | D70: Inv. Banking & Broker | E70: 4
A71: 30202000 | B71: 113 | C71: DIVFS | D71: Div. Fin. Services | E71: 5
B72: 113 | C72: DIVFS | D72: Div. Fin. Services | E72: 6
A73: 30202010 | B73: 104 | C73: ASSET | D73: Asset Mngr, Custodian | E73: 5
B74: 104 | C74: ASSET | D74: Asset Mngr, Custodian | E74: 6
A75: 30202015 | B75: 111 | C75: INVSV | D75: Investment Services | E75: 5
B76: 111 | C76: INVSV | D76: Investment Services | E76: 6
A77: 302030 | B77: 165 | C77: RITMG | D77: Mortgage REITs | E77: 4
A78: 30203000 | B78: 237 | C78: RITMD | D78: Mge REITs: Divers. | E78: 5
B79: 237 | C79: RITMD | D79: Mge REITs: Divers. | E79: 6
A80: 30203010 | B80: 236 | C80: RITMC | D80: Mge REITs: Comm. | E80: 5
B81: 236 | C81: RITMC | D81: Mge REITs: Comm. | E81: 6
A82: 30203020 | B82: 238 | C82: RITMR | D82: Mge REITs: Resid. | E82: 5
B83: 238 | C83: RITMR | D83: Mge REITs: Resid. | E83: 6
A84: 302040 | B84: 23 | C84: CEINV | D84: Closed End Invest. | E84: 4
A85: 30204000 | B85: 23 | C85: CEINV | D85: Closed End Invest. | E85: 5
B86: 77 | C86: INVNK | D86: Investment Companies | E86: 6
B87: 109 | C87: ITINT | D87: Investment Trusts | E87: 6
B88: 76 | C88: ITPEQ | D88: Private Equity | E88: 6
B89: 149 | C89: ITVCT | D89: Venture Capital Trust | E89: 6
A90: 302050 | B90: 4 | C90: OMINV | D90: Open, Misc. Invest. | E90: 4
A91: 30205000 | B91: 4 | C91: OMINV | D91: Open, Misc. Invest. | E91: 5
B92: 159 | C92: EXTRF | D92: Exchange Traded Funds | E92: 6
B93: 154 | C93: EXTRN | D93: Exchange Traded Notes | E93: 6
B94: 170 | C94: EXTRC | D94: Exc. Traded Commodity | E94: 6
B95: 147 | C95: ITHSI | D95: Housing Incm. Inv.Tst | E95: 6
B96: 148 | C96: OEINC | D96: Open Ended Inv. Cos. | E96: 6
B97: 136 | C97: OFFSH | D97: Offshore Funds | E97: 6
B98: 121 | C98: CURFD | D98: Currency Funds | E98: 6
B99: 137 | C99: INVTO | D99: Other Inv. Trusts | E99: 6
B100: 73 | C100: ITSPL | D100: Split Capital Inv.Tst | E100: 6
...
